Metadata-Version: 2.4
Name: svc_order_zxw
Version: 2.3.20
Summary: 订单与支付服务: 支持苹果内购订阅
Home-page: https://github.com/sunshineinwater/
Author: 薛伟的小工具
Author-email: jingmu_app@foxmail.com
Classifier: Programming Language :: Python :: 3.10
Classifier: License :: OSI Approved :: MIT License
Classifier: Operating System :: OS Independent
Requires-Dist: fastapi<0.113,>=0.112.0
Requires-Dist: sqlalchemy==2.0.32
Requires-Dist: greenlet==3.0.3
Requires-Dist: asyncpg==0.29.0
Requires-Dist: psycopg2-binary>=2.9.10
Requires-Dist: uvicorn<0.31.0,>=0.30.0
Requires-Dist: app-tools-zxw>=2.2.4
Dynamic: author
Dynamic: author-email
Dynamic: classifier
Dynamic: description
Dynamic: description-content-type
Dynamic: home-page
Dynamic: requires-dist
Dynamic: summary
